MANIFEST.in
requirements.txt
setup.py
xosconfig/VERSION
xosconfig/__init__.py
xosconfig/config.py
xosconfig/default.py
xosconfig/synchronizer-config-schema.yaml
xosconfig/version.py
xosconfig/xos-config-schema.yaml
xosconfig.egg-info/PKG-INFO
xosconfig.egg-info/SOURCES.txt
xosconfig.egg-info/dependency_links.txt
xosconfig.egg-info/requires.txt
xosconfig.egg-info/top_level.txt