Metadata-Version: 1.1
Name: xosconfig
Version: 3.0.7
Summary: XOS Config Library
Home-page: https://gerrit.opencord.org/gitweb?p=xos.git
Author: Matteo Scandolo
Author-email: cord-dev@opencord.org
License: Apache v2
Platform: UNKNOWN
Classifier: License :: OSI Approved :: Apache Software License
